pypromql/__init__.py
pypromql/connection.py
pypromql/query/__init__.py
pypromql/query/prometheus_label.py
pypromql/query/prometheus_query.py
pypromql/query/prometheus_query_builder.py
pypromql/result/__init__.py
pypromql/result/prometheus_metric.py
pypromql/result/prometheus_result.py
tests/__init__.py
tests/query/__init__.py
tests/query/test_query.py
tests/result/__init__.py
tests/result/test_result.py
PyPromql-0.0.3.dist-info/LICENSE
PyPromql-0.0.3.dist-info/METADATA
PyPromql-0.0.3.dist-info/WHEEL
PyPromql-0.0.3.dist-info/top_level.txt
PyPromql-0.0.3.dist-info/RECORD
