Metadata-Version: 2.1
Name: PyPromql
Version: 0.0.3
Summary: PyPromql is a Python library that simplifies the creation and execution of PromQL queries.
Home-page: https://github.com/aviv-levi/pypromql.git
Author: Aviv Levi
Author-email: 60aviv60@gmail.com
License: MIT
Keywords: pypromql,py-promql,prometheus-query-builder,promql-query-builder
Classifier: Development Status :: 5 - Production/Stable
Classifier: Intended Audience :: Developers
Classifier: License :: OSI Approved :: MIT License
Classifier: Operating System :: OS Independent
Classifier: Programming Language :: Python :: 3
Classifier: Programming Language :: Python :: 3.6
Classifier: Programming Language :: Python :: 3.7
Classifier: Programming Language :: Python :: 3.8
Classifier: Programming Language :: Python :: 3.9
License-File: LICENSE
Requires-Dist: pytest
Requires-Dist: requests
